{
  "$schema": "https://developer.microsoft.com/json-schemas/fabric/item/report/definition/visualContainer/2.5.0/schema.json",
  "name": "c3d4e5f6a7b801c2d3e4",
  "position": {
    "x": 856,
    "y": 112,
    "z": 1000,
    "height": 288,
    "width": 211,
    "tabOrder": 7000
  },
  "visual": {
    "visualType": "card",
    "query": {
      "queryState": {
        "Values": {
          "projections": [
            {
              "field": {
                "Measure": {
                  "Expression": {
                    "SourceRef": {
                      "Entity": "FACT_MEDALLA"
                    }
                  },
                  "Property": "Medallas Femeninas"
                }
              },
              "queryRef": "FACT_MEDALLA.Medallas Femeninas",
              "active": true
            }
          ]
        }
      }
    },
    "drillFilterOtherVisuals": true
  }
}